inchpym/ManejoArchivos.py
inchpym/ManejoDataframe.py
inchpym/ManejoLiquidacion.py
inchpym/__init__.py
inchpym-0.1.20.dist-info/licenses/LICENSE
inchpym-0.1.20.dist-info/METADATA
inchpym-0.1.20.dist-info/WHEEL
inchpym-0.1.20.dist-info/top_level.txt
inchpym-0.1.20.dist-info/RECORD
