Metadata-Version: 2.4
Name: inchpym
Version: 0.1.20
Summary: Librería de Python para manejo de archivos y DataFrames de Daniel Ochoa
Author-email: DanielOchoa <df.ochoa202@gmail.com>
Requires-Python: >=3.8
License-File: LICENSE
Requires-Dist: pandas>=2.0.0
Requires-Dist: numpy>=1.26.0
Requires-Dist: unidecode>=1.3.6
Requires-Dist: openpyxl>=3.1.0
Requires-Dist: pywin32>=306
Dynamic: license-file
